buptlibrecord/__init__.py
buptlibrecord-0.0.1.dist-info/LICENSE
buptlibrecord-0.0.1.dist-info/METADATA
buptlibrecord-0.0.1.dist-info/WHEEL
buptlibrecord-0.0.1.dist-info/entry_points.txt
buptlibrecord-0.0.1.dist-info/top_level.txt
buptlibrecord-0.0.1.dist-info/RECORD
